Metadata-Version: 1.1
Name: icstools
Version: 0.2.1
Summary: cat/grep-like for icalendar calendar files (.ics)
Home-page: https://code.crapouillou.net/jocelyn/icstools
Author: Jocelyn Delalande
Author-email: jocelyn@crapouillou.net
License: UNKNOWN
Platform: UNKNOWN
Classifier: Topic :: Office/Business :: Scheduling
Classifier: License :: OSI Approved :: GNU General Public License v3 or later (GPLv3+)
Classifier: Programming Language :: Python :: 3 :: Only
